aklite/__init__.py
aklite/stock/__init__.py
aklite/stock/stock_hist_em.py
aklite-0.0.4.dist-info/METADATA
aklite-0.0.4.dist-info/WHEEL
aklite-0.0.4.dist-info/licenses/LICENSE
aklite-0.0.4.dist-info/RECORD
